Metadata-Version: 2.1
Name: JELSR
Version: 0.0.1
Summary: JELSR_Feature_Selection
Home-page: https://github.com/hanhe2018/JELSR
Author: hanhe
Author-email: hanhe@ucdavis.edu
License: UNKNOWN
Platform: UNKNOWN
Classifier: Programming Language :: Python :: 3
Classifier: License :: OSI Approved :: MIT License
Classifier: Operating System :: OS Independent
